{
  "major_version": 1,
  "minor_version": 0,
  "bones": [
    {
      "name": "Trans",
      "transform": [
        [
          1.0,
          0.0,
          0.0,
          0.0
        ],
        [
          0.0,
          1.0,
          0.0,
          0.0
        ],
        [
          0.0,
          0.0,
          1.0,
          0.0
        ],
        [
          0.0,
          0.0,
          0.0,
          1.0
        ]
      ],
      "parent_index": null,
      "billboard_type": "Disabled"
    },
    {
      "name": "Rot",
      "transform": [
        [
          1.0,
          0.0,
          0.0,
          0.0
        ],
        [
          0.0,
          1.0,
          0.0,
          0.0
        ],
        [
          0.0,
          0.0,
          1.0,
          0.0
        ],
        [
          0.0,
          8.48057,
          0.323443,
          1.0
        ]
      ],
      "parent_index": 0,
      "billboard_type": "Disabled"
    },
    {
      "name": "Hip",
      "transform": [
        [
          0.0,
          0.942024,
          0.335546,
          0.0
        ],
        [
          0.0,
          -0.335546,
          0.942024,
          0.0
        ],
        [
          1.0,
          0.0,
          0.0,
          0.0
        ],
        [
          0.0,
          0.0,
          0.0,
          1.0
        ]
      ],
      "parent_index": 1,
      "billboard_type": "Disabled"
    },
    {
      "name": "Waist",
      "transform": [
        [
          0.883166,
          -0.469061,
          0.0,
          0.0
        ],
        [
          0.469061,
          0.883166,
          0.0,
          0.0
        ],
        [
          0.0,
          0.0,
          1.0,
          0.0
        ],
        [
          1.20007,
          0.0,
          0.0,
          1.0
        ]
      ],
      "parent_index": 2,
      "billboard_type": "Disabled"
    },
    {
      "name": "Bust",
      "transform": [
        [
          0.999996,
          -0.00270693,
          0.0,
          0.0
        ],
        [
          0.00270693,
          0.999996,
          0.0,
          0.0
        ],
        [
          0.0,
          0.0,
          1.0,
          0.0
        ],
        [
          1.18052,
          0.0,
          0.0,
          1.0
        ]
      ],
      "parent_index": 3,
      "billboard_type": "Disabled"
    },
    {
      "name": "Neck",
      "transform": [
        [
          0.871712,
          0.490019,
          0.0,
          0.0
        ],
        [
          -0.490019,
          0.871712,
          0.0,
          0.0
        ],
        [
          0.0,
          0.0,
          1.0,
          0.0
        ],
        [
          1.99543,
          0.0,
          0.0,
          1.0
        ]
      ],
      "parent_index": 4,
      "billboard_type": "Disabled"
    },
    {
      "name": "Head",
      "transform": [
        [
          0.934706,
          -0.355421,
          0.0,
          0.0
        ],
        [
          0.355421,
          0.934706,
          0.0,
          0.0
        ],
        [
          0.0,
          0.0,
          1.0,
          0.0
        ],
        [
          1.19018,
          0.0,
          0.0,
          1.0
        ]
      ],
      "parent_index": 5,
      "billboard_type": "Disabled"
    },
    {
      "name": "Mouth",
      "transform": [
        [
          0.0,
          1.0,
          0.0,
          0.0
        ],
        [
          -1.0,
          0.0,
          0.0,
          0.0
        ],
        [
          0.0,
          0.0,
          1.0,
          0.0
        ],
        [
          -0.153134,
          0.38568,
          0.0,
          1.0
        ]
      ],
      "parent_index": 6,
      "billboard_type": "Disabled"
    },
    {
      "name": "ClavicleC",
      "transform": [
        [
          0.988958,
          0.148198,
          0.0,
          0.0
        ],
        [
          -0.148198,
          0.988958,
          0.0,
          0.0
        ],
        [
          0.0,
          0.0,
          1.0,
          0.0
        ],
        [
          1.26254,
          -0.00230558,
          0.0,
          1.0
        ]
      ],
      "parent_index": 4,
      "billboard_type": "Disabled"
    },
    {
      "name": "ClavicleL",
      "transform": [
        [
          0.0,
          0.0,
          1.0,
          0.0
        ],
        [
          0.0,
          1.0,
          0.0,
          0.0
        ],
        [
          -1.0,
          0.0,
          0.0,
          0.0
        ],
        [
          0.0,
          0.0,
          0.695804,
          1.0
        ]
      ],
      "parent_index": 8,
      "billboard_type": "Disabled"
    },
    {
      "name": "ShoulderL",
      "transform": [
        [
          0.993289,
          -0.115268,
          0.00954502,
          0.0
        ],
        [
          0.115273,
          0.993334,
          0.0,
          0.0
        ],
        [
          -0.00948139,
          0.00110029,
          0.999954,
          0.0
        ],
        [
          1.19718,
          -0.264709,
          0.566747,
          1.0
        ]
      ],
      "parent_index": 9,
      "billboard_type": "Disabled"
    },
    {
      "name": "ArmL",
      "transform": [
        [
          0.989049,
          0.147149,
          -0.0113442,
          0.0
        ],
        [
          -0.147158,
          0.989113,
          0.0,
          0.0
        ],
        [
          0.0112207,
          0.0016694,
          0.999936,
          0.0
        ],
        [
          2.66652,
          0.0,
          0.0,
          1.0
        ]
      ],
      "parent_index": 10,
      "billboard_type": "Disabled"
    },
    {
      "name": "HandL",
      "transform": [
        [
          0.999481,
          -0.0321525,
          0.00185704,
          0.0
        ],
        [
          -0.00190329,
          -0.00140771,
          0.999997,
          0.0
        ],
        [
          -0.0321498,
          -0.999482,
          -0.00146817,
          0.0
        ],
        [
          2.43263,
          0.0,
          0.0,
          1.0
        ]
      ],
      "parent_index": 11,
      "billboard_type": "Disabled"
    },
    {
      "name": "HaveL",
      "transform": [
        [
          0.0,
          -1.0,
          0.0,
          0.0
        ],
        [
          0.0,
          0.0,
          -1.0,
          0.0
        ],
        [
          1.0,
          0.0,
          0.0,
          0.0
        ],
        [
          1.08863,
          0.288555,
          -0.129598,
          1.0
        ]
      ],
      "parent_index": 12,
      "billboard_type": "Disabled"
    },
    {
      "name": "ClavicleR",
      "transform": [
        [
          0.0,
          0.0,
          -1.0,
          0.0
        ],
        [
          0.0,
          1.0,
          0.0,
          0.0
        ],
        [
          1.0,
          0.0,
          0.0,
          0.0
        ],
        [
          0.0,
          0.0,
          -0.695804,
          1.0
        ]
      ],
      "parent_index": 8,
      "billboard_type": "Disabled"
    },
    {
      "name": "ShoulderR",
      "transform": [
        [
          0.993289,
          -0.115268,
          -0.00952518,
          0.0
        ],
        [
          0.115274,
          0.993334,
          0.0,
          0.0
        ],
        [
          0.00946168,
          -0.001098,
          0.999955,
          0.0
        ],
        [
          1.19719,
          -0.264709,
          -0.566799,
          1.0
        ]
      ],
      "parent_index": 14,
      "billboard_type": "Disabled"
    },
    {
      "name": "ArmR",
      "transform": [
        [
          0.989053,
          0.147129,
          0.0113111,
          0.0
        ],
        [
          -0.147138,
          0.989116,
          0.0,
          0.0
        ],
        [
          -0.011188,
          -0.00166429,
          0.999936,
          0.0
        ],
        [
          2.66652,
          0.0,
          0.0,
          1.0
        ]
      ],
      "parent_index": 15,
      "billboard_type": "Disabled"
    },
    {
      "name": "HandR",
      "transform": [
        [
          0.999482,
          -0.0321317,
          -0.00184364,
          0.0
        ],
        [
          -0.00188975,
          -0.00140459,
          -0.999997,
          0.0
        ],
        [
          0.032129,
          0.999483,
          -0.00146458,
          0.0
        ],
        [
          2.43419,
          0.0,
          0.0,
          1.0
        ]
      ],
      "parent_index": 16,
      "billboard_type": "Disabled"
    },
    {
      "name": "HaveR",
      "transform": [
        [
          0.0,
          1.0,
          0.0,
          0.0
        ],
        [
          0.0,
          0.0,
          1.0,
          0.0
        ],
        [
          1.0,
          0.0,
          0.0,
          0.0
        ],
        [
          1.08746,
          0.288558,
          0.129598,
          1.0
        ]
      ],
      "parent_index": 17,
      "billboard_type": "Disabled"
    },
    {
      "name": "Tail1",
      "transform": [
        [
          -0.335546,
          -0.942024,
          0.0,
          0.0
        ],
        [
          0.942024,
          -0.335546,
          0.0,
          0.0
        ],
        [
          0.0,
          0.0,
          1.0,
          0.0
        ],
        [
          -0.244449,
          -0.967301,
          0.0,
          1.0
        ]
      ],
      "parent_index": 2,
      "billboard_type": "Disabled"
    },
    {
      "name": "Tail2",
      "transform": [
        [
          1.0,
          0.0,
          0.0,
          0.0
        ],
        [
          0.0,
          1.0,
          0.0,
          0.0
        ],
        [
          0.0,
          0.0,
          1.0,
          0.0
        ],
        [
          2.98252,
          0.0,
          0.0,
          1.0
        ]
      ],
      "parent_index": 19,
      "billboard_type": "Disabled"
    },
    {
      "name": "Reflector",
      "transform": [
        [
          -0.873932,
          0.311292,
          0.373283,
          0.0
        ],
        [
          0.335546,
          0.942024,
          0.0,
          0.0
        ],
        [
          -0.351641,
          0.125254,
          -0.927718,
          0.0
        ],
        [
          0.540351,
          -0.109414,
          1.40944,
          1.0
        ]
      ],
      "parent_index": 2,
      "billboard_type": "Disabled"
    },
    {
      "name": "LegC",
      "transform": [
        [
          0.942023,
          -0.335548,
          0.0,
          0.0
        ],
        [
          0.335548,
          0.942023,
          0.0,
          0.0
        ],
        [
          0.0,
          0.0,
          1.0,
          0.0
        ],
        [
          -0.463991,
          0.383359,
          0.0,
          1.0
        ]
      ],
      "parent_index": 2,
      "billboard_type": "Disabled"
    },
    {
      "name": "LegL",
      "transform": [
        [
          -0.999233,
          -0.0387419,
          -0.00569263,
          0.0
        ],
        [
          0.0387426,
          -0.999249,
          0.0,
          0.0
        ],
        [
          -0.00568835,
          -0.000220547,
          0.999984,
          0.0
        ],
        [
          0.0,
          0.0,
          1.0,
          1.0
        ]
      ],
      "parent_index": 22,
      "billboard_type": "Disabled"
    },
    {
      "name": "KneeL",
      "transform": [
        [
          0.999738,
          0.0219186,
          0.00658934,
          0.0
        ],
        [
          -0.0219191,
          0.99976,
          0.0,
          0.0
        ],
        [
          -0.00658775,
          -0.000144432,
          0.999978,
          0.0
        ],
        [
          3.17865,
          0.0,
          0.0,
          1.0
        ]
      ],
      "parent_index": 23,
      "billboard_type": "Disabled"
    },
    {
      "name": "FootL",
      "transform": [
        [
          0.99816,
          -0.0606343,
          -0.000888877,
          0.0
        ],
        [
          0.0606342,
          0.99816,
          -0.000179003,
          0.0
        ],
        [
          0.000898096,
          0.000124777,
          1.0,
          0.0
        ],
        [
          3.32088,
          0.0,
          0.0,
          1.0
        ]
      ],
      "parent_index": 24,
      "billboard_type": "Disabled"
    },
    {
      "name": "ToeL",
      "transform": [
        [
          0.0,
          -1.0,
          0.0,
          0.0
        ],
        [
          1.0,
          0.0,
          0.0,
          0.0
        ],
        [
          0.0,
          0.0,
          1.0,
          0.0
        ],
        [
          0.79757,
          -1.98394,
          0.0973036,
          1.0
        ]
      ],
      "parent_index": 25,
      "billboard_type": "Disabled"
    },
    {
      "name": "LegR",
      "transform": [
        [
          -0.999233,
          -0.0387416,
          0.00566354,
          0.0
        ],
        [
          0.0387423,
          -0.999249,
          0.0,
          0.0
        ],
        [
          0.00565928,
          0.000219418,
          0.999984,
          0.0
        ],
        [
          0.0,
          0.0,
          -1.0,
          1.0
        ]
      ],
      "parent_index": 22,
      "billboard_type": "Disabled"
    },
    {
      "name": "KneeR",
      "transform": [
        [
          0.999738,
          0.0219191,
          -0.0065602,
          0.0
        ],
        [
          -0.0219195,
          0.99976,
          0.0,
          0.0
        ],
        [
          0.00655863,
          0.000143797,
          0.999978,
          0.0
        ],
        [
          3.17866,
          0.0,
          0.0,
          1.0
        ]
      ],
      "parent_index": 27,
      "billboard_type": "Disabled"
    },
    {
      "name": "FootR",
      "transform": [
        [
          0.99816,
          -0.0606345,
          0.000888865,
          0.0
        ],
        [
          0.0606343,
          0.99816,
          0.000178366,
          0.0
        ],
        [
          -0.000898045,
          -0.000124142,
          1.0,
          0.0
        ],
        [
          3.32088,
          0.0,
          0.0,
          1.0
        ]
      ],
      "parent_index": 28,
      "billboard_type": "Disabled"
    },
    {
      "name": "ToeR",
      "transform": [
        [
          0.0,
          -1.0,
          0.0,
          0.0
        ],
        [
          1.0,
          0.0,
          0.0,
          0.0
        ],
        [
          0.0,
          0.0,
          1.0,
          0.0
        ],
        [
          0.797573,
          -1.98395,
          -0.097307,
          1.0
        ]
      ],
      "parent_index": 29,
      "billboard_type": "Disabled"
    },
    {
      "name": "Throw",
      "transform": [
        [
          1.0,
          0.0,
          0.0,
          0.0
        ],
        [
          0.0,
          1.0,
          0.0,
          0.0
        ],
        [
          0.0,
          0.0,
          1.0,
          0.0
        ],
        [
          0.0,
          -8.48057,
          -0.323443,
          1.0
        ]
      ],
      "parent_index": 1,
      "billboard_type": "Disabled"
    },
    {
      "name": "FingerL10",
      "transform": [
        [
          1.0,
          0.0,
          0.0,
          0.0
        ],
        [
          0.0,
          1.0,
          0.0,
          0.0
        ],
        [
          0.0,
          0.0,
          1.0,
          0.0
        ],
        [
          0.05,
          0.0,
          -0.16,
          1.0
        ]
      ],
      "parent_index": 12,
      "billboard_type": "Disabled"
    },
    {
      "name": "FingerL20",
      "transform": [
        [
          1.0,
          0.0,
          0.0,
          0.0
        ],
        [
          0.0,
          1.0,
          0.0,
          0.0
        ],
        [
          0.0,
          0.0,
          1.0,
          0.0
        ],
        [
          0.0,
          0.0,
          0.16,
          1.0
        ]
      ],
      "parent_index": 32,
      "billboard_type": "Disabled"
    },
    {
      "name": "FingerL30",
      "transform": [
        [
          1.0,
          0.0,
          0.0,
          0.0
        ],
        [
          0.0,
          1.0,
          0.0,
          0.0
        ],
        [
          0.0,
          0.0,
          1.0,
          0.0
        ],
        [
          0.0,
          0.0,
          0.16,
          1.0
        ]
      ],
      "parent_index": 33,
      "billboard_type": "Disabled"
    },
    {
      "name": "FingerL40",
      "transform": [
        [
          1.0,
          0.0,
          0.0,
          0.0
        ],
        [
          0.0,
          1.0,
          0.0,
          0.0
        ],
        [
          0.0,
          0.0,
          1.0,
          0.0
        ],
        [
          0.0,
          0.0,
          0.16,
          1.0
        ]
      ],
      "parent_index": 34,
      "billboard_type": "Disabled"
    },
    {
      "name": "FingerL41",
      "transform": [
        [
          1.0,
          0.0,
          0.0,
          0.0
        ],
        [
          0.0,
          1.0,
          0.0,
          0.0
        ],
        [
          0.0,
          0.0,
          1.0,
          0.0
        ],
        [
          0.756404,
          -0.0999621,
          0.673482,
          1.0
        ]
      ],
      "parent_index": 35,
      "billboard_type": "Disabled"
    },
    {
      "name": "FingerL42",
      "transform": [
        [
          1.0,
          0.0,
          0.0,
          0.0
        ],
        [
          0.0,
          1.0,
          0.0,
          0.0
        ],
        [
          0.0,
          0.0,
          1.0,
          0.0
        ],
        [
          0.279846,
          0.0,
          0.0,
          1.0
        ]
      ],
      "parent_index": 36,
      "billboard_type": "Disabled"
    },
    {
      "name": "FingerL43",
      "transform": [
        [
          1.0,
          0.0,
          0.0,
          0.0
        ],
        [
          0.0,
          1.0,
          0.0,
          0.0
        ],
        [
          0.0,
          0.0,
          1.0,
          0.0
        ],
        [
          0.2494,
          0.0,
          0.0,
          1.0
        ]
      ],
      "parent_index": 37,
      "billboard_type": "Disabled"
    },
    {
      "name": "FingerL31",
      "transform": [
        [
          1.0,
          0.0,
          0.0,
          0.0
        ],
        [
          0.0,
          1.0,
          0.0,
          0.0
        ],
        [
          0.0,
          0.0,
          1.0,
          0.0
        ],
        [
          0.992001,
          -0.0894753,
          0.268456,
          1.0
        ]
      ],
      "parent_index": 34,
      "billboard_type": "Disabled"
    },
    {
      "name": "FingerL32",
      "transform": [
        [
          1.0,
          0.0,
          0.0,
          0.0
        ],
        [
          0.0,
          1.0,
          0.0,
          0.0
        ],
        [
          0.0,
          0.0,
          1.0,
          0.0
        ],
        [
          0.38989,
          0.0,
          0.0,
          1.0
        ]
      ],
      "parent_index": 39,
      "billboard_type": "Disabled"
    },
    {
      "name": "FingerL33",
      "transform": [
        [
          1.0,
          0.0,
          0.0,
          0.0
        ],
        [
          0.0,
          1.0,
          0.0,
          0.0
        ],
        [
          0.0,
          0.0,
          1.0,
          0.0
        ],
        [
          0.296804,
          0.0,
          0.0,
          1.0
        ]
      ],
      "parent_index": 40,
      "billboard_type": "Disabled"
    },
    {
      "name": "FingerL21",
      "transform": [
        [
          1.0,
          0.0,
          0.0,
          0.0
        ],
        [
          0.0,
          1.0,
          0.0,
          0.0
        ],
        [
          0.0,
          0.0,
          1.0,
          0.0
        ],
        [
          1.11747,
          -0.0964116,
          -0.0683371,
          1.0
        ]
      ],
      "parent_index": 33,
      "billboard_type": "Disabled"
    },
    {
      "name": "FingerL22",
      "transform": [
        [
          1.0,
          0.0,
          0.0,
          0.0
        ],
        [
          0.0,
          1.0,
          0.0,
          0.0
        ],
        [
          0.0,
          0.0,
          1.0,
          0.0
        ],
        [
          0.410421,
          0.0,
          0.0,
          1.0
        ]
      ],
      "parent_index": 42,
      "billboard_type": "Disabled"
    },
    {
      "name": "FingerL23",
      "transform": [
        [
          1.0,
          0.0,
          0.0,
          0.0
        ],
        [
          0.0,
          1.0,
          0.0,
          0.0
        ],
        [
          0.0,
          0.0,
          1.0,
          0.0
        ],
        [
          0.493824,
          0.0,
          0.0,
          1.0
        ]
      ],
      "parent_index": 43,
      "billboard_type": "Disabled"
    },
    {
      "name": "FingerL11",
      "transform": [
        [
          1.0,
          0.0,
          0.0,
          0.0
        ],
        [
          0.0,
          1.0,
          0.0,
          0.0
        ],
        [
          0.0,
          0.0,
          1.0,
          0.0
        ],
        [
          1.08564,
          -0.103359,
          -0.450893,
          1.0
        ]
      ],
      "parent_index": 32,
      "billboard_type": "Disabled"
    },
    {
      "name": "FingerL12",
      "transform": [
        [
          1.0,
          0.0,
          0.0,
          0.0
        ],
        [
          0.0,
          1.0,
          0.0,
          0.0
        ],
        [
          0.0,
          0.0,
          1.0,
          0.0
        ],
        [
          0.470314,
          0.0,
          0.0,
          1.0
        ]
      ],
      "parent_index": 45,
      "billboard_type": "Disabled"
    },
    {
      "name": "FingerL13",
      "transform": [
        [
          1.0,
          0.0,
          0.0,
          0.0
        ],
        [
          0.0,
          1.0,
          0.0,
          0.0
        ],
        [
          0.0,
          0.0,
          1.0,
          0.0
        ],
        [
          0.63022,
          0.0,
          0.0,
          1.0
        ]
      ],
      "parent_index": 46,
      "billboard_type": "Disabled"
    },
    {
      "name": "FingerL51",
      "transform": [
        [
          0.739942,
          0.198267,
          -0.642788,
          0.0
        ],
        [
          0.566509,
          0.331569,
          0.754407,
          0.0
        ],
        [
          0.362703,
          -0.922362,
          0.133022,
          0.0
        ],
        [
          0.12,
          0.116289,
          -0.526703,
          1.0
        ]
      ],
      "parent_index": 32,
      "billboard_type": "Disabled"
    },
    {
      "name": "FingerL52",
      "transform": [
        [
          0.907673,
          0.330366,
          0.258819,
          0.0
        ],
        [
          -0.34202,
          0.939693,
          0.0,
          0.0
        ],
        [
          -0.24321,
          -0.0885213,
          0.965926,
          0.0
        ],
        [
          0.424723,
          0.0,
          0.0,
          1.0
        ]
      ],
      "parent_index": 48,
      "billboard_type": "Disabled"
    },
    {
      "name": "FingerL53",
      "transform": [
        [
          0.984808,
          0.173648,
          0.0,
          0.0
        ],
        [
          -0.173648,
          0.984808,
          0.0,
          0.0
        ],
        [
          0.0,
          0.0,
          1.0,
          0.0
        ],
        [
          0.427606,
          0.0,
          0.0,
          1.0
        ]
      ],
      "parent_index": 49,
      "billboard_type": "Disabled"
    },
    {
      "name": "FingerR10",
      "transform": [
        [
          1.0,
          0.0,
          0.0,
          0.0
        ],
        [
          0.0,
          1.0,
          0.0,
          0.0
        ],
        [
          0.0,
          0.0,
          1.0,
          0.0
        ],
        [
          0.05,
          0.0,
          0.16,
          1.0
        ]
      ],
      "parent_index": 17,
      "billboard_type": "Disabled"
    },
    {
      "name": "FingerR20",
      "transform": [
        [
          1.0,
          0.0,
          0.0,
          0.0
        ],
        [
          0.0,
          1.0,
          0.0,
          0.0
        ],
        [
          0.0,
          0.0,
          1.0,
          0.0
        ],
        [
          0.0,
          0.0,
          -0.16,
          1.0
        ]
      ],
      "parent_index": 51,
      "billboard_type": "Disabled"
    },
    {
      "name": "FingerR30",
      "transform": [
        [
          1.0,
          0.0,
          0.0,
          0.0
        ],
        [
          0.0,
          1.0,
          0.0,
          0.0
        ],
        [
          0.0,
          0.0,
          1.0,
          0.0
        ],
        [
          0.0,
          0.0,
          -0.16,
          1.0
        ]
      ],
      "parent_index": 52,
      "billboard_type": "Disabled"
    },
    {
      "name": "FingerR40",
      "transform": [
        [
          1.0,
          0.0,
          0.0,
          0.0
        ],
        [
          0.0,
          1.0,
          0.0,
          0.0
        ],
        [
          0.0,
          0.0,
          1.0,
          0.0
        ],
        [
          0.0,
          0.0,
          -0.16,
          1.0
        ]
      ],
      "parent_index": 53,
      "billboard_type": "Disabled"
    },
    {
      "name": "FingerR41",
      "transform": [
        [
          1.0,
          0.0,
          0.0,
          0.0
        ],
        [
          0.0,
          1.0,
          0.0,
          0.0
        ],
        [
          0.0,
          0.0,
          1.0,
          0.0
        ],
        [
          0.756404,
          -0.0999621,
          -0.673482,
          1.0
        ]
      ],
      "parent_index": 54,
      "billboard_type": "Disabled"
    },
    {
      "name": "FingerR42",
      "transform": [
        [
          1.0,
          0.0,
          0.0,
          0.0
        ],
        [
          0.0,
          1.0,
          0.0,
          0.0
        ],
        [
          0.0,
          0.0,
          1.0,
          0.0
        ],
        [
          0.279846,
          0.0,
          0.0,
          1.0
        ]
      ],
      "parent_index": 55,
      "billboard_type": "Disabled"
    },
    {
      "name": "FingerR43",
      "transform": [
        [
          1.0,
          0.0,
          0.0,
          0.0
        ],
        [
          0.0,
          1.0,
          0.0,
          0.0
        ],
        [
          0.0,
          0.0,
          1.0,
          0.0
        ],
        [
          0.2494,
          0.0,
          0.0,
          1.0
        ]
      ],
      "parent_index": 56,
      "billboard_type": "Disabled"
    },
    {
      "name": "FingerR31",
      "transform": [
        [
          1.0,
          0.0,
          0.0,
          0.0
        ],
        [
          0.0,
          1.0,
          0.0,
          0.0
        ],
        [
          0.0,
          0.0,
          1.0,
          0.0
        ],
        [
          0.992001,
          -0.0894753,
          -0.268456,
          1.0
        ]
      ],
      "parent_index": 53,
      "billboard_type": "Disabled"
    },
    {
      "name": "FingerR32",
      "transform": [
        [
          1.0,
          0.0,
          0.0,
          0.0
        ],
        [
          0.0,
          1.0,
          0.0,
          0.0
        ],
        [
          0.0,
          0.0,
          1.0,
          0.0
        ],
        [
          0.38989,
          0.0,
          0.0,
          1.0
        ]
      ],
      "parent_index": 58,
      "billboard_type": "Disabled"
    },
    {
      "name": "FingerR33",
      "transform": [
        [
          1.0,
          0.0,
          0.0,
          0.0
        ],
        [
          0.0,
          1.0,
          0.0,
          0.0
        ],
        [
          0.0,
          0.0,
          1.0,
          0.0
        ],
        [
          0.296804,
          0.0,
          0.0,
          1.0
        ]
      ],
      "parent_index": 59,
      "billboard_type": "Disabled"
    },
    {
      "name": "FingerR21",
      "transform": [
        [
          1.0,
          0.0,
          0.0,
          0.0
        ],
        [
          0.0,
          1.0,
          0.0,
          0.0
        ],
        [
          0.0,
          0.0,
          1.0,
          0.0
        ],
        [
          1.11747,
          -0.0964116,
          0.0683371,
          1.0
        ]
      ],
      "parent_index": 52,
      "billboard_type": "Disabled"
    },
    {
      "name": "FingerR22",
      "transform": [
        [
          1.0,
          0.0,
          0.0,
          0.0
        ],
        [
          0.0,
          1.0,
          0.0,
          0.0
        ],
        [
          0.0,
          0.0,
          1.0,
          0.0
        ],
        [
          0.410421,
          0.0,
          0.0,
          1.0
        ]
      ],
      "parent_index": 61,
      "billboard_type": "Disabled"
    },
    {
      "name": "FingerR23",
      "transform": [
        [
          1.0,
          0.0,
          0.0,
          0.0
        ],
        [
          0.0,
          1.0,
          0.0,
          0.0
        ],
        [
          0.0,
          0.0,
          1.0,
          0.0
        ],
        [
          0.493824,
          0.0,
          0.0,
          1.0
        ]
      ],
      "parent_index": 62,
      "billboard_type": "Disabled"
    },
    {
      "name": "FingerR11",
      "transform": [
        [
          1.0,
          0.0,
          0.0,
          0.0
        ],
        [
          0.0,
          1.0,
          0.0,
          0.0
        ],
        [
          0.0,
          0.0,
          1.0,
          0.0
        ],
        [
          1.08564,
          -0.103359,
          0.450893,
          1.0
        ]
      ],
      "parent_index": 51,
      "billboard_type": "Disabled"
    },
    {
      "name": "FingerR12",
      "transform": [
        [
          1.0,
          0.0,
          0.0,
          0.0
        ],
        [
          0.0,
          1.0,
          0.0,
          0.0
        ],
        [
          0.0,
          0.0,
          1.0,
          0.0
        ],
        [
          0.470314,
          0.0,
          0.0,
          1.0
        ]
      ],
      "parent_index": 64,
      "billboard_type": "Disabled"
    },
    {
      "name": "FingerR13",
      "transform": [
        [
          1.0,
          0.0,
          0.0,
          0.0
        ],
        [
          0.0,
          1.0,
          0.0,
          0.0
        ],
        [
          0.0,
          0.0,
          1.0,
          0.0
        ],
        [
          0.63022,
          0.0,
          0.0,
          1.0
        ]
      ],
      "parent_index": 65,
      "billboard_type": "Disabled"
    },
    {
      "name": "FingerR51",
      "transform": [
        [
          0.739942,
          0.198267,
          0.642788,
          0.0
        ],
        [
          0.566509,
          0.331569,
          -0.754407,
          0.0
        ],
        [
          -0.362703,
          0.922362,
          0.133022,
          0.0
        ],
        [
          0.12,
          0.116289,
          0.526703,
          1.0
        ]
      ],
      "parent_index": 51,
      "billboard_type": "Disabled"
    },
    {
      "name": "FingerR52",
      "transform": [
        [
          0.907673,
          0.330366,
          -0.258819,
          0.0
        ],
        [
          -0.34202,
          0.939693,
          0.0,
          0.0
        ],
        [
          0.24321,
          0.0885213,
          0.965926,
          0.0
        ],
        [
          0.424723,
          0.0,
          0.0,
          1.0
        ]
      ],
      "parent_index": 67,
      "billboard_type": "Disabled"
    },
    {
      "name": "FingerR53",
      "transform": [
        [
          0.984808,
          0.173648,
          0.0,
          0.0
        ],
        [
          -0.173648,
          0.984808,
          0.0,
          0.0
        ],
        [
          0.0,
          0.0,
          1.0,
          0.0
        ],
        [
          0.427606,
          0.0,
          0.0,
          1.0
        ]
      ],
      "parent_index": 68,
      "billboard_type": "Disabled"
    },
    {
      "name": "H_ElbowL",
      "transform": [
        [
          1.0,
          0.0,
          0.0,
          0.0
        ],
        [
          0.0,
          1.0,
          0.0,
          0.0
        ],
        [
          0.0,
          0.0,
          1.0,
          0.0
        ],
        [
          2.71619,
          0.00576366,
          -0.00047407,
          1.0
        ]
      ],
      "parent_index": 10,
      "billboard_type": "Disabled"
    },
    {
      "name": "H_SholderL",
      "transform": [
        [
          1.0,
          0.0,
          0.0,
          0.0
        ],
        [
          0.0,
          1.0,
          0.0,
          0.0
        ],
        [
          0.0,
          0.0,
          1.0,
          0.0
        ],
        [
          1.24718,
          -0.264709,
          0.566747,
          1.0
        ]
      ],
      "parent_index": 9,
      "billboard_type": "Disabled"
    },
    {
      "name": "H_ElbowR",
      "transform": [
        [
          1.0,
          0.0,
          0.0,
          0.0
        ],
        [
          0.0,
          1.0,
          0.0,
          0.0
        ],
        [
          0.0,
          0.0,
          1.0,
          0.0
        ],
        [
          2.71618,
          0.00576368,
          0.000473084,
          1.0
        ]
      ],
      "parent_index": 15,
      "billboard_type": "Disabled"
    },
    {
      "name": "H_SholderR",
      "transform": [
        [
          1.0,
          0.0,
          0.0,
          0.0
        ],
        [
          0.0,
          1.0,
          0.0,
          0.0
        ],
        [
          0.0,
          0.0,
          1.0,
          0.0
        ],
        [
          1.24719,
          -0.264709,
          -0.566799,
          1.0
        ]
      ],
      "parent_index": 14,
      "billboard_type": "Disabled"
    }
  ]
}